{
   "title": "Song of Solomon",
   "teachings": [
      {
         "series": "Thru-The-Bible Studies - 7000 Series",
         "date": "03-02-16",
         "title": "Song Of Solomon 1-4",
         "passage": "Song Of Solomon 1-4",
         "event": "Verse by Verse Bible Study",
         "teachingNumber": "W7206",
         "media": {
            "link": "https://cdn.jwplayer.com/previews/6ZR0aTuj",
            "duration": 4149,
            "pubdate": 1481160838,
            "source": {
               "file": "https://cdn.jwplayer.com/videos/6ZR0aTuj-LDq1jMq6.m4a",
               "type": "audio/mp4",
               "label": "AAC Audio",
               "bitrate": 113376,
               "filesize": 58803422
            }
         },
         "link": "https://www.joncourson.com/playteaching/W7206",
         "guid": "4a424bcf-e40c-522f-b13b-738095467f0b"
      },
      {
         "series": "Thru-The-Bible Studies - 7000 Series",
         "date": "03-09-16",
         "title": "Song Of Solomon 5-8",
         "passage": "Song Of Solomon 5-8",
         "event": "Verse by Verse Bible Study",
         "teachingNumber": "W7207",
         "media": {
            "link": "https://cdn.jwplayer.com/previews/vJfydhT1",
            "duration": 3668,
            "pubdate": 1481160838,
            "source": {
               "file": "https://cdn.jwplayer.com/videos/vJfydhT1-LDq1jMq6.m4a",
               "type": "audio/mp4",
               "label": "AAC Audio",
               "bitrate": 113376,
               "filesize": 51985766
            }
         },
         "link": "https://www.joncourson.com/playteaching/W7207",
         "guid": "c20ccb95-8413-58e4-860a-d16a8b3efe4a"
      },
      {
         "series": "Thru-The-Bible Studies",
         "date": "07-12-87",
         "title": "My Life - His Garden - Song of Solomon 4:12 - 5:1",
         "passage": "Song of Solomon 4:12 - 5:1",
         "event": "Sunday Sermon",
         "teachingNumber": "S353",
         "media": {
            "link": "https://cdn.jwplayer.com/previews/D2NupLvM",
            "duration": 1936,
            "pubdate": 1481154139,
            "source": {
               "file": "https://cdn.jwplayer.com/videos/D2NupLvM-LDq1jMq6.m4a",
               "type": "audio/mp4",
               "label": "AAC Audio",
               "bitrate": 113376,
               "filesize": 27440525
            }
         },
         "link": "https://www.joncourson.com/playteaching/S353",
         "guid": "da9f4193-e4fa-535e-9032-4d709e3cfa63"
      },
      {
         "series": "Thru-The-Bible Studies",
         "date": "07-15-87",
         "title": "Song of Solomon 1-2",
         "passage": "Song of Solomon 1-2",
         "event": "Verse by Verse Bible Study",
         "teachingNumber": "W388",
         "media": {
            "link": "https://cdn.jwplayer.com/previews/6QkoOCtK",
            "duration": 4014,
            "pubdate": 1481156390,
            "source": {
               "file": "https://cdn.jwplayer.com/videos/6QkoOCtK-LDq1jMq6.m4a",
               "type": "audio/mp4",
               "label": "AAC Audio",
               "bitrate": 113376,
               "filesize": 56894689
            }
         },
         "link": "https://www.joncourson.com/playteaching/W388",
         "guid": "213dfd57-9c4b-56f8-9277-b322a81b698c"
      },
      {
         "series": "Thru-The-Bible Studies",
         "date": "07-19-87",
         "title": "The Glory Of The Church - Song of Solomon 6:10",
         "passage": "Song of Solomon 6:10",
         "event": "Sunday Sermon",
         "teachingNumber": "S354",
         "media": {
            "link": "https://cdn.jwplayer.com/previews/RkPJiSyO",
            "duration": 2774,
            "pubdate": 1481154139,
            "source": {
               "file": "https://cdn.jwplayer.com/videos/RkPJiSyO-LDq1jMq6.m4a",
               "type": "audio/mp4",
               "label": "AAC Audio",
               "bitrate": 113376,
               "filesize": 39321421
            }
         },
         "link": "https://www.joncourson.com/playteaching/S354",
         "guid": "7d059cc2-7722-5a4a-b054-57a64fdad70b"
      },
      {
         "series": "Thru-The-Bible Studies",
         "date": "07-22-87",
         "title": "Song of Solomon 2-5",
         "passage": "Song of Solomon 2-5",
         "event": "Verse by Verse Bible Study",
         "teachingNumber": "W389",
         "media": {
            "link": "https://cdn.jwplayer.com/previews/9A7k7l9p",
            "duration": 4036,
            "pubdate": 1481156390,
            "source": {
               "file": "https://cdn.jwplayer.com/videos/9A7k7l9p-LDq1jMq6.m4a",
               "type": "audio/mp4",
               "label": "AAC Audio",
               "bitrate": 113376,
               "filesize": 57204835
            }
         },
         "link": "https://www.joncourson.com/playteaching/W389",
         "guid": "815f3ee1-e781-5f94-8adb-87456fb8aadb"
      },
      {
         "series": "Thru-The-Bible Studies",
         "date": "07-26-87",
         "title": "A Loving Look At Our Lovely Lord - Song of Solomon 5:9-16",
         "passage": "Song of Solomon 5:9-16",
         "event": "Sunday Sermon",
         "teachingNumber": "S355",
         "media": {
            "link": "https://cdn.jwplayer.com/previews/GGsJp75e",
            "duration": 2682,
            "pubdate": 1481154139,
            "source": {
               "file": "https://cdn.jwplayer.com/videos/GGsJp75e-LDq1jMq6.m4a",
               "type": "audio/mp4",
               "label": "AAC Audio",
               "bitrate": 113376,
               "filesize": 38015164
            }
         },
         "link": "https://www.joncourson.com/playteaching/S355",
         "guid": "e2fa6bcb-aaa1-5d6f-99fc-7f1d2c3d9437"
      },
      {
         "series": "Thru-The-Bible Studies",
         "date": "07-29-87",
         "title": "Song of Solomon 5-8",
         "passage": "Song of Solomon 5-8",
         "event": "Verse by Verse Bible Study",
         "teachingNumber": "W390",
         "media": {
            "link": "https://cdn.jwplayer.com/previews/Jup9boxp",
            "duration": 4113,
            "pubdate": 1481156390,
            "source": {
               "file": "https://cdn.jwplayer.com/videos/Jup9boxp-LDq1jMq6.m4a",
               "type": "audio/mp4",
               "label": "AAC Audio",
               "bitrate": 113376,
               "filesize": 58295109
            }
         },
         "link": "https://www.joncourson.com/playteaching/W390",
         "guid": "8155f7ff-3164-546e-a6bb-ec8d8db4ec19"
      },
      {
         "series": "Miscellaneous Bible Studies",
         "date": "07-13-84",
         "title": "Let The Wind Blow, Lord!",
         "passage": "Let The Wind Blow, Lord!",
         "event": "Song of Solomon 4:12-16",
         "teachingNumber": "T105",
         "media": {
            "link": "https://cdn.jwplayer.com/previews/KcBptTZO",
            "duration": 1029,
            "pubdate": 1481162165,
            "source": {
               "file": "https://cdn.jwplayer.com/videos/KcBptTZO-LDq1jMq6.m4a",
               "type": "audio/mp4",
               "label": "AAC Audio",
               "bitrate": 113384,
               "filesize": 14590075
            }
         },
         "link": "https://www.joncourson.com/playteaching/T105",
         "guid": "40f22f9a-2dcb-56c5-9d76-8463b598d54b"
      }
   ],
   "books": [
      "Song of Solomon"
   ]
}